aiopytesseract/__init__.py
aiopytesseract/_logger.py
aiopytesseract/base_command.py
aiopytesseract/commands.py
aiopytesseract/constants.py
aiopytesseract/exceptions.py
aiopytesseract/file_format.py
aiopytesseract/returncode.py
aiopytesseract/validators.py
aiopytesseract/models/__init__.py
aiopytesseract/models/box.py
aiopytesseract/models/data.py
aiopytesseract/models/osd.py
aiopytesseract/models/parameter.py
aiopytesseract-1.0.0.dist-info/licenses/LICENSE
aiopytesseract-1.0.0.dist-info/WHEEL
aiopytesseract-1.0.0.dist-info/METADATA
aiopytesseract-1.0.0.dist-info/RECORD
