Metadata-Version: 2.4
Name: aiopytesseract
Version: 1.0.0
Summary: asyncio tesseract wrapper for Tesseract-OCR
Keywords: asyncio,ocr,tesseract
Author-email: Alexandre Menezes <alexandre.fmenezes@gmail.com>
Requires-Python: >=3.11
Classifier: Development Status :: 5 - Production/Stable
Classifier: Framework :: AsyncIO
Classifier: Intended Audience :: Developers
Classifier: License :: OSI Approved :: Apache Software License
Classifier: Operating System :: OS Independent
Classifier: Programming Language :: Python :: 3 :: Only
Classifier: Programming Language :: Python :: 3.11
Classifier: Programming Language :: Python :: 3.12
Classifier: Programming Language :: Python :: 3.13
Classifier: Programming Language :: Python :: Implementation :: CPython
Classifier: Programming Language :: Python :: Implementation :: PyPy
Classifier: Topic :: Software Development :: Libraries
License-File: LICENSE
Requires-Dist: aiofiles
Requires-Dist: attrs
Requires-Dist: cattrs
Requires-Dist: mkdocs-material ; extra == "all"
Requires-Dist: streamlit ; extra == "all"
Requires-Dist: mypy ; extra == "dev"
Requires-Dist: types-aiofiles ; extra == "dev"
Requires-Dist: pytest ; extra == "dev"
Requires-Dist: pytest-cov ; extra == "dev"
Requires-Dist: pytest-asyncio ; extra == "dev"
Requires-Dist: pre-commit ; extra == "dev"
Requires-Dist: ruff ; extra == "dev"
Requires-Dist: bandit ; extra == "dev"
Requires-Dist: detect-secrets ; extra == "dev"
Requires-Dist: mkdocs-material ; extra == "docs"
Requires-Dist: streamlit ; extra == "streamlit"
Project-URL: Changes, https://github.com/amenezes/aiopytesseract/releases
Project-URL: Code, https://github.com/amenezes/aiopytesseract
Project-URL: Documentation, https://github.com/amenezes/aiopytesseract
Project-URL: Issue tracker, https://github.com/amenezes/aiopytesseract/issues
Provides-Extra: all
Provides-Extra: dev
Provides-Extra: docs
Provides-Extra: streamlit
